[
  {
    "question": "The Bible passage for Lesson 16 (Destiny Destroyers) is",
    "options": [
      "1 Kings 11:1-6",
      "Jeremiah 29:11",
      "Jeremiah 1:5",
      "Hosea 4:6"
    ],
    "type": "multiple-choice",
    "answer": "1 Kings 11:1-6"
  },
  {
    "question": "The memory verse for Lesson 16 is from",
    "options": [
      "1 Kings 11:1-6",
      "Jeremiah 29:11",
      "Jeremiah 1:5",
      "Hosea 4:6"
    ],
    "type": "multiple-choice",
    "answer": "Jeremiah 29:11"
  },
  {
    "question": "The memory verse says God's thoughts toward us are thoughts of peace and not of evil, to give us a future and a ________",
    "type": "fill-in-the-blank",
    "answer": "Hope"
  },
  {
    "question": "Destiny is God's divine purpose and pre-planned destination for a person's",
    "options": [
      "life",
      "future",
      "calling",
      "journey"
    ],
    "type": "multiple-choice",
    "answer": "life"
  },
  {
    "question": "Destiny represents what God has ordained for an individual even before",
    "options": [
      "conception",
      "birth",
      "salvation",
      "calling"
    ],
    "type": "multiple-choice",
    "answer": "conception"
  },
  {
    "question": "The destiny destroyer that is a lack of knowledge of God's plan for our lives is ________ (Hosea 4:6)",
    "type": "fill-in-the-blank",
    "answer": "Ignorance"
  },
  {
    "question": "Solomon's pursuit of vanity and wealth led to his backsliding; this destiny destroyer is",
    "options": [
      "Pursuit of Vanity",
      "Pride",
      "Lack of Faith",
      "Anger"
    ],
    "type": "multiple-choice",
    "answer": "Pursuit of Vanity"
  },
  {
    "question": "The destiny destroyer that hinders our ability to trust and rely on God's guidance is",
    "options": [
      "Lack of Faith",
      "Pride",
      "Anger",
      "Laziness"
    ],
    "type": "multiple-choice",
    "answer": "Lack of Faith"
  },
  {
    "question": "The destiny destroyer described as unreasonable and inordinate self-esteem leading to a fall is",
    "options": [
      "Pride",
      "Anger",
      "Laziness",
      "Ignorance"
    ],
    "type": "multiple-choice",
    "answer": "Pride"
  },
  {
    "question": "Pride leads to divine resistance according to",
    "options": [
      "James 4:6",
      "Hosea 4:6",
      "1 Timothy 1:19",
      "Proverbs 12:24"
    ],
    "type": "multiple-choice",
    "answer": "James 4:6"
  },
  {
    "question": "Unconfessed sin provokes God's anger; this destiny destroyer is 'Sinful ________'",
    "type": "fill-in-the-blank",
    "answer": "Lifestyles"
  },
  {
    "question": "The destiny destroyer where uncontrolled emotion causes individuals to deviate from God's purpose is",
    "options": [
      "Anger",
      "Pride",
      "Laziness",
      "Ignorance"
    ],
    "type": "multiple-choice",
    "answer": "Anger"
  },
  {
    "question": "The destiny destroyer of slothfulness that prevents individuals from fulfilling their potential is",
    "options": [
      "Laziness",
      "Anger",
      "Pride",
      "Prayerlessness"
    ],
    "type": "multiple-choice",
    "answer": "Laziness"
  },
  {
    "question": "The destiny destroyer that creates openings for the enemy to attack one's destiny is",
    "options": [
      "Prayerlessness",
      "Laziness",
      "Anger",
      "Pride"
    ],
    "type": "multiple-choice",
    "answer": "Prayerlessness"
  },
  {
    "question": "Which biblical figure allowed greed and betrayal to destroy his destiny by betraying Jesus?",
    "options": [
      "Judas Iscariot",
      "Demas",
      "Gehazi",
      "Reuben"
    ],
    "type": "multiple-choice",
    "answer": "Judas Iscariot"
  },
  {
    "question": "Which once-companion of Paul abandoned his faith and ministry, choosing worldly desires?",
    "options": [
      "Demas",
      "Judas Iscariot",
      "Gehazi",
      "Achan"
    ],
    "type": "multiple-choice",
    "answer": "Demas"
  },
  {
    "question": "Which greedy servant of Elisha lied and took gifts unlawfully, resulting in leprosy?",
    "options": [
      "Gehazi",
      "Demas",
      "Reuben",
      "Achan"
    ],
    "type": "multiple-choice",
    "answer": "Gehazi"
  },
  {
    "question": "Which of Jacob's firstborn lost his birthright due to illicit sex with his father's concubine?",
    "options": [
      "Reuben",
      "Judas Iscariot",
      "Gehazi",
      "Achan"
    ],
    "type": "multiple-choice",
    "answer": "Reuben"
  },
  {
    "question": "Whose disobedience in taking spoils from Jericho led to the destruction of his family?",
    "options": [
      "Achan",
      "Reuben",
      "Gehazi",
      "Demas"
    ],
    "type": "multiple-choice",
    "answer": "Achan"
  },
  {
    "question": "True knowledge of the truth sets us free and guides us toward our destiny (John 8:________)",
    "type": "fill-in-the-blank",
    "answer": "32"
  },
  {
    "question": "The lesson aim for Lesson 16 is to study some destiny destroyers and victims of destiny",
    "options": [
      "destroyers",
      "destruction",
      "forces",
      "enemies"
    ],
    "type": "multiple-choice",
    "answer": "destroyers"
  },
  {
    "question": "Failure to align with God's will may expose us to destiny destroyers that could derail or hinder the fulfilment of God's",
    "options": [
      "plan",
      "purpose",
      "will",
      "destiny"
    ],
    "type": "multiple-choice",
    "answer": "plan"
  },
  {
    "question": "Demas's love for the world ultimately led to the destruction of his destiny, per",
    "options": [
      "2 Timothy 4:10",
      "Matthew 27:35",
      "2 Kings 5:20-27",
      "Genesis 49:3-4"
    ],
    "type": "multiple-choice",
    "answer": "2 Timothy 4:10"
  },
  {
    "question": "Slothfulness leaves individuals perpetually under the influence of more ________ individuals (Proverbs 12:24)",
    "type": "fill-in-the-blank",
    "answer": "Industrious"
  },
  {
    "question": "The conclusion of Lesson 16 says to avoid destiny destroyers, we must fully surrender to God and align ourselves with His",
    "options": [
      "will",
      "word",
      "plan",
      "purpose"
    ],
    "type": "multiple-choice",
    "answer": "will"
  },
  {
    "question": "Gehazi's action resulted in the curse of leprosy upon him and his",
    "options": [
      "descendants",
      "household",
      "family",
      "children"
    ],
    "type": "multiple-choice",
    "answer": "descendants"
  },
  {
    "question": "The opening prayer for Lesson 16 asks the Father to frustrate every destroyer of destiny lurking",
    "options": [
      "around me",
      "in my path",
      "near me",
      "in my life"
    ],
    "type": "multiple-choice",
    "answer": "around me"
  },
  {
    "question": "By staying obedient and trusting in God's direction, we can walk in the fullness of the destiny He has",
    "options": [
      "prepared for us",
      "given us",
      "planned for us",
      "ordained for us"
    ],
    "type": "multiple-choice",
    "answer": "prepared for us"
  },
  {
    "question": "Achan's sin resulted in the loss of his life and that of his ________",
    "type": "fill-in-the-blank",
    "answer": "Household"
  },
  {
    "question": "The teaching method for Lesson 16 is",
    "options": [
      "Lecture and Discussion Methods",
      "The Lecture Method",
      "The Discussion Method",
      "The Question and Answer Method"
    ],
    "type": "multiple-choice",
    "answer": "Lecture and Discussion Methods"
  }
]